{
    "display": {
        "icon": {
            "item": "minecraft:player_head",
            "nbt": "{SkullOwner:{Id:[I;-1767051932,1535462297,-1205513267,2057279270],Name:'Magma Cube',Properties:{textures:[{Value:'eyJ0ZXh0dXJlcyI6eyJTS0lOIjp7InVybCI6Imh0dHA6Ly90ZXh0dXJlcy5taW5lY3JhZnQubmV0L3RleHR1cmUvMzg5NTdkNTAyM2M5MzdjNGM0MWFhMjQxMmQ0MzQxMGJkYTIzY2Y3OWE5ZjZhYjM2Yjc2ZmVmMmQ3YzQyOSJ9fX0='}]}}}"
        },
        "title": {
            "translate": "A magma cube was killed!"
        },
        "description": {
            "translate": "Kill a magma cube"
        },
        "frame": "task",
        "show_toast": true,
        "hidden": false,
        "announce_to_chat": false
    },
    "criteria": {
      "kill": {
          "trigger": "minecraft:player_killed_entity",
          "conditions": {
              "entity": {
                  "type": "minecraft:magma_cube"
              }
          }
      }
    },
    "parent":"kill-all:mobs/husk",
    "rewards": {
        "function": "kill-all:mobs/magma_cube"
    }
}
